aoyunwuhuan.py
love.py
setup.py
Love_Wuhuan.egg-info/PKG-INFO
Love_Wuhuan.egg-info/SOURCES.txt
Love_Wuhuan.egg-info/dependency_links.txt
Love_Wuhuan.egg-info/top_level.txt