Metadata-Version: 2.1
Name: Love-Wuhuan
Version: 1.0.0
Summary: 海龟画图-奥运五环以及告白爱心
Home-page: UNKNOWN
Author: eno
License: UNKNOWN
Platform: UNKNOWN
